[
    {
        "companyLogo": "googlelogo",
        "companyName": "Google",
        "jobLocation": "USA",
        "jobRole": "Senior Product Designer",
        "description": "Design, develop, and maintain software applications. Write clean, efficient code, troubleshoot issues, and collaborate with teams to deliver high-quality solutions. Stay updated with industry trends and continuously improve skills.",
        "nPositions": "2",
        "roleType": "Full Time",
        "pay": 5000000
    },
    {
        "companyLogo": "amazonlogo",
        "companyName": "Amazon",
        "jobLocation": "USA",
        "jobRole": "Software Engineer",
        "description": "Develop, test, and maintain software applications. Collaborate with cross-functional teams to deliver high-quality solutions.",
        "nPositions": "5",
        "roleType": "Full Time",
        "pay": 3500000
    },
    {
        "companyLogo": "applelogo",
        "companyName": "Apple",
        "jobLocation": "USA",
        "jobRole": "UI/UX Designer",
        "description": "Design user interfaces and experiences for mobile and web applications. Work closely with developers to implement designs.",
        "nPositions": "3",
        "roleType": "Full Time",
        "pay": 800000
    },
    {
        "companyLogo": "eylogo",
        "companyName": "EY",
        "jobLocation": "USA",
        "jobRole": "Data Scientist",
        "description": "Analyze large datasets to extract insights and inform business decisions. Develop predictive models and algorithms.",
        "nPositions": "4",
        "roleType": "Full Time",
        "pay": 140000
    },
    {
        "companyLogo": "figmalogo",
        "companyName": "Figma",
        "jobLocation": "USA",
        "jobRole": "Backend Developer",
        "description": "Develop and maintain server-side logic, databases, and APIs. Ensure high performance and responsiveness of applications.",
        "nPositions": "2",
        "roleType": "Full Time",
        "pay": 135000
    },
    {
        "companyLogo": "netflixlogo",
        "companyName": "Netflix",
        "jobLocation": "USA",
        "jobRole": "Frontend Developer",
        "description": "Develop and maintain user-facing features for web applications. Ensure high performance and responsiveness of applications.",
        "nPositions": "3",
        "roleType": "Full Time",
        "pay": 125000
    },
    {
        "companyLogo": "googlelogo",
        "companyName": "Google",
        "jobLocation": "USA",
        "jobRole": "DevOps Engineer",
        "description": "Implement and manage CI/CD pipelines. Ensure the reliability and scalability of infrastructure.",
        "nPositions": "2",
        "roleType": "Full Time",
        "pay": 130000
    },
    {
        "companyLogo": "nvidialogo",
        "companyName": "Nvidia",
        "jobLocation": "USA",
        "jobRole": "Mobile Developer",
        "description": "Develop and maintain mobile applications for iOS and Android. Ensure high performance and responsiveness of applications.",
        "nPositions": "4",
        "roleType": "Full Time",
        "pay": 120000
    },
    {
        "companyLogo": "bnblogo",
        "companyName": "Airbnb",
        "jobLocation": "USA",
        "jobRole": "Full Stack Developer",
        "description": "Develop and maintain both frontend and backend components of web applications. Ensure high performance and responsiveness of applications.",
        "nPositions": "3",
        "roleType": "Full Time",
        "pay": 130000
    },
    {
        "companyLogo": "spotifylogo",
        "companyName": "Spotify",
        "jobLocation": "USA",
        "jobRole": "Machine Learning Engineer",
        "description": "Develop and deploy machine learning models. Collaborate with data scientists and engineers to build scalable solutions.",
        "nPositions": "2",
        "roleType": "Full Time",
        "pay": 145000
    },
    {
        "companyLogo": "nvidialogo",
        "companyName": "Nvidia",
        "jobLocation": "USA",
        "jobRole": "Site Reliability Engineer",
        "description": "Ensure the reliability and scalability of infrastructure. Implement monitoring and alerting systems.",
        "nPositions": "3",
        "roleType": "Full Time",
        "pay": 135000
    },
    {
        "companyLogo": "amazonlogo",
        "companyName": "Amazon",
        "jobLocation": "USA",
        "jobRole": "Security Engineer",
        "description": "Implement and manage security measures to protect systems and data. Conduct security assessments and audits.",
        "nPositions": "2",
        "roleType": "Full Time",
        "pay": 140000
    },
    {
        "companyLogo": "slsfrslogo",
        "companyName": "Salesforce",
        "jobLocation": "USA",
        "jobRole": "Cloud Engineer",
        "description": "Design and implement cloud-based solutions. Ensure the reliability and scalability of cloud infrastructure.",
        "nPositions": "3",
        "roleType": "Full Time",
        "pay": 135000
    },
    {
        "companyLogo": "amazonlogo",
        "companyName": "Amazon",
        "jobLocation": "USA",
        "jobRole": "Product Manager",
        "description": "Define product vision and strategy. Collaborate with cross-functional teams to deliver high-quality products.",
        "nPositions": "2",
        "roleType": "Full Time",
        "pay": 150000
    },
    {
        "companyLogo": "netflixlogo",
        "companyName": "Netflix",
        "jobLocation": "USA",
        "jobRole": "Hardware Engineer",
        "description": "Design and develop hardware components. Collaborate with software engineers to ensure compatibility and performance.",
        "nPositions": "3",
        "roleType": "Full Time",
        "pay": 130000
    },
    {
        "companyLogo": "ibmlogo",
        "companyName": "IBM",
        "jobLocation": "USA",
        "jobRole": "Systems Engineer",
        "description": "Design and implement IT systems and infrastructure. Ensure the reliability and scalability of systems.",
        "nPositions": "2",
        "roleType": "Full Time",
        "pay": 125000
    }
]